setup.cfg
setup.py
ec3/__init__.py
ec3/__main__.py
ec3/args.py
ec3/boto_cache.py
ec3/compat.py
ec3/config.py
ec3/ec2_searcher.py
ec3/env_dict.py
ec3/exceptions.py
ec3/main.py
ec3/main_shell.py
ec3/main_ssh.py
ec3/util.py
ec3/version.py
ec3.egg-info/PKG-INFO
ec3.egg-info/SOURCES.txt
ec3.egg-info/dependency_links.txt
ec3.egg-info/entry_points.txt
ec3.egg-info/requires.txt
ec3.egg-info/top_level.txt
ec3.egg-info/zip-safe