Metadata-Version: 1.0
Name: ec3
Version: 0.9.2
Summary: tag-based ec2 instance SSH with environment variable configuration
Home-page: http://github.com/scivey/ec3
Author: Scott Ivey
Author-email: scott.ivey@gmail.com
License: UNKNOWN
Platform: UNKNOWN
